litds/__init__.py
litds/_modidx.py
litds/imps.py
litds/types.py
litds/utils.py
litds/abc/__init__.py
litds/abc/dfdm/__init__.py
litds/abc/dfdm/base.py
litds/abc/dfdm/meta.py
litds/abc/dfds/__init__.py
litds/abc/dfds/base.py
litds/abc/dfds/meta.py
litds/abc/dfds/mixs.py
litds/abc/idxs/__init__.py
litds/abc/idxs/base.py
litds/abc/idxs/cloc.py
litds/abc/idxs/iloc.py
litds/abc/idxs/loc.py
litds/abc/idxs/meta.py
litds/abc/mock/__init__.py
litds/abc/mock/base.py
litds/abc/mock/meta.py
litds/core/__init__.py
litds/core/dfdm.py
litds/core/dfds.py
litds/datasets/__init__.py
litds/datasets/diamonds.py
litds/datasets/embryoid.py
litds/datasets/orbits.py
litds/fetch/__init__.py
litds/fetch/pbmc.py
litds/mocks/__init__.py
litds/mocks/adata.py
litds/mocks/time.py
litds/named/__init__.py
litds/named/arr.py
litds/named/trj.py
litds/time/__init__.py
litds/time/base.py
litds/time/mixs.py
litds/time/series.py
litds-0.0.3.dist-info/LICENSE
litds-0.0.3.dist-info/METADATA
litds-0.0.3.dist-info/WHEEL
litds-0.0.3.dist-info/entry_points.txt
litds-0.0.3.dist-info/top_level.txt
litds-0.0.3.dist-info/RECORD
