Metadata-Version: 2.1
Name: litds
Version: 0.0.3
Summary: litds
Home-page: https://github.com/dsm-72/litds
Author: dsm-72
Author-email: sumner.magruder@yale.edu
License: Apache Software License 2.0
Keywords: nbdev jupyter notebook python
Classifier: Development Status :: 4 - Beta
Classifier: Intended Audience :: Developers
Classifier: Natural Language :: English
Classifier: Programming Language :: Python :: 3.7
Classifier: Programming Language :: Python :: 3.8
Classifier: Programming Language :: Python :: 3.9
Classifier: Programming Language :: Python :: 3.10
Classifier: License :: OSI Approved :: Apache Software License
Requires-Python: >=3.7
License-File: LICENSE
Requires-Dist: pandas
Requires-Dist: seaborn
Requires-Dist: scikit-learn
Requires-Dist: numpy
Requires-Dist: nbformat
Requires-Dist: rich
Requires-Dist: typer
Requires-Dist: requests
Requires-Dist: tqdm
Requires-Dist: ipos
Requires-Dist: iza
Requires-Dist: torch
Requires-Dist: pytorch-lightning
Requires-Dist: beartype
Requires-Dist: nptyping
Requires-Dist: littyping
Requires-Dist: scanpy
Requires-Dist: anndata
Requires-Dist: scprep
Requires-Dist: phate
Requires-Dist: kuut
Requires-Dist: degex
Provides-Extra: dev
